<?xml version="1.0" encoding="UTF-8"?>
<!DOCTYPE suite SYSTEM "http://testng.org/testng-1.0.dtd">
<suite name="All Test Suite">
    <listeners>
        <listener class-name="listener.ScreenshotListener"></listener>
    </listeners>
    <test verbose="2" preserve-order="true" name="tests">
        <classes>
            <class name="uiTest.reportsTest.ReportsIconAndLinkTest">
                <methods>
                    <include name="openReportsIconAndLink"/>
                </methods>
            </class>
        </classes>
    </test>
</suite>